README.md
setup.cfg
setup.py
py_hydropi/__init__.py
py_hydropi/main.py
py_hydropi.egg-info/PKG-INFO
py_hydropi.egg-info/SOURCES.txt
py_hydropi.egg-info/dependency_links.txt
py_hydropi.egg-info/entry_points.txt
py_hydropi.egg-info/requires.txt
py_hydropi.egg-info/top_level.txt
py_hydropi/lib/GPIO.py
py_hydropi/lib/__init__.py
py_hydropi/lib/config.py
py_hydropi/lib/events.py
py_hydropi/lib/iter_utils.py
py_hydropi/lib/logger.py
py_hydropi/lib/memdatabase.py
py_hydropi/lib/threaded_daemon.py
py_hydropi/lib/time_utils.py
py_hydropi/lib/API/__init__.py
py_hydropi/lib/API/api_endpoint_base.py
py_hydropi/lib/API/main.py
py_hydropi/lib/metrics/__init__.py
py_hydropi/lib/metrics/collector_controller.py
py_hydropi/lib/metrics/collectors/__init__.py
py_hydropi/lib/metrics/collectors/output.py
py_hydropi/lib/metrics/collectors/sensor.py
py_hydropi/lib/metrics/reporters/__init__.py
py_hydropi/lib/metrics/reporters/influxdb.py
py_hydropi/lib/modules/__init__.py
py_hydropi/lib/modules/inputs.py
py_hydropi/lib/modules/outputs.py
py_hydropi/lib/modules/switch.py
py_hydropi/lib/modules/threshold_switch.py
py_hydropi/lib/modules/timer.py
py_hydropi/lib/modules/sensors/__init__.py
py_hydropi/lib/modules/sensors/dhtxx.py
py_hydropi/lib/modules/sensors/hc_sr04.py
py_hydropi/lib/modules/sensors/homelab_ph.py
py_hydropi/lib/modules/sensors/one_wire.py