Metadata-Version: 1.1
Name: py-hydropi
Version: 0.0.11.post1542345774
Summary: Hydroponics controller for RaspberryPi
Home-page: https://github.com/chestm007/py_hydropi
Author: max
Author-email: chestm007@hotmail.com
License: GPL-2.0
Platform: UNKNOWN
Requires: PyYAML
Requires: cherrypy
Requires: systemd
Requires: pep8
Requires: requests
